<annotation>
	<folder>Array-list</folder>
	<filename>List_80.png</filename>
	<path>D:\temp\CSDQA\diagram\Array-list\List_80.png</path>
	<source>
		<database>Unknown</database>
	</source>
	<size>
		<width>604</width>
		<height>126</height>
		<depth>1</depth>
	</size>
	<segmented>0</segmented>
	<object>
		<name>list</name>
		<pose>Unspecified</pose>
		<truncated>0</truncated>
		<difficult>0</difficult>
		<bndbox>
			<xmin>33</xmin>
			<ymin>66</ymin>
			<xmax>552</xmax>
			<ymax>113</ymax>
		</bndbox>
	</object>
	<object>
		<name>middle</name>
		<pose>Unspecified</pose>
		<truncated>0</truncated>
		<difficult>0</difficult>
		<bndbox>
			<xmin>176</xmin>
			<ymin>66</ymin>
			<xmax>221</xmax>
			<ymax>112</ymax>
		</bndbox>
	</object>
	<object>
		<name>answer</name>
		<pose>Unspecified</pose>
		<truncated>0</truncated>
		<difficult>0</difficult>
		<bndbox>
			<xmin>194</xmin>
			<ymin>83</ymin>
			<xmax>203</xmax>
			<ymax>94</ymax>
		</bndbox>
	</object>
</annotation>
