<annotation>
	<folder>Network-topology</folder>
	<filename>38.png</filename>
	<path>C:\Users\lenovo\Desktop\diagram\Network-topology\38.png</path>
	<source>
		<database>Unknown</database>
	</source>
	<size>
		<width>658</width>
		<height>617</height>
		<depth>3</depth>
	</size>
	<segmented>0</segmented>
	<object>
		<name>network</name>
		<pose>Unspecified</pose>
		<truncated>0</truncated>
		<difficult>0</difficult>
		<bndbox>
			<xmin>15</xmin>
			<ymin>69</ymin>
			<xmax>617</xmax>
			<ymax>439</ymax>
		</bndbox>
	</object>
	<object>
		<name>node</name>
		<pose>Unspecified</pose>
		<truncated>0</truncated>
		<difficult>0</difficult>
		<bndbox>
			<xmin>47</xmin>
			<ymin>71</ymin>
			<xmax>149</xmax>
			<ymax>143</ymax>
		</bndbox>
	</object>
	<object>
		<name>node</name>
		<pose>Unspecified</pose>
		<truncated>0</truncated>
		<difficult>0</difficult>
		<bndbox>
			<xmin>153</xmin>
			<ymin>357</ymin>
			<xmax>237</xmax>
			<ymax>430</ymax>
		</bndbox>
	</object>
	<object>
		<name>node</name>
		<pose>Unspecified</pose>
		<truncated>0</truncated>
		<difficult>0</difficult>
		<bndbox>
			<xmin>373</xmin>
			<ymin>359</ymin>
			<xmax>470</xmax>
			<ymax>435</ymax>
		</bndbox>
	</object>
	<object>
		<name>node</name>
		<pose>Unspecified</pose>
		<truncated>0</truncated>
		<difficult>0</difficult>
		<bndbox>
			<xmin>259</xmin>
			<ymin>73</ymin>
			<xmax>336</xmax>
			<ymax>148</ymax>
		</bndbox>
	</object>
	<object>
		<name>node</name>
		<pose>Unspecified</pose>
		<truncated>0</truncated>
		<difficult>0</difficult>
		<bndbox>
			<xmin>455</xmin>
			<ymin>72</ymin>
			<xmax>545</xmax>
			<ymax>151</ymax>
		</bndbox>
	</object>
	<object>
		<name>center of the structure</name>
		<pose>Unspecified</pose>
		<truncated>0</truncated>
		<difficult>0</difficult>
		<bndbox>
			<xmin>274</xmin>
			<ymin>208</ymin>
			<xmax>350</xmax>
			<ymax>286</ymax>
		</bndbox>
	</object>
</annotation>
