<annotation>
	<folder>Flowchart</folder>
	<filename>99.png</filename>
	<path>C:\Users\CYT\Desktop\CSDQA_v2.1\CSDQA_v2.1\data\diagram\Flowchart\99.png</path>
	<source>
		<database>Unknown</database>
	</source>
	<size>
		<width>225</width>
		<height>225</height>
		<depth>3</depth>
	</size>
	<segmented>0</segmented>
	<object>
		<name>diagram</name>
		<pose>Unspecified</pose>
		<truncated>0</truncated>
		<difficult>0</difficult>
		<bndbox>
			<xmin>19</xmin>
			<ymin>6</ymin>
			<xmax>207</xmax>
			<ymax>218</ymax>
		</bndbox>
	</object>
	<object>
		<name>flowchart</name>
		<pose>Unspecified</pose>
		<truncated>0</truncated>
		<difficult>0</difficult>
		<bndbox>
			<xmin>19</xmin>
			<ymin>6</ymin>
			<xmax>208</xmax>
			<ymax>217</ymax>
		</bndbox>
	</object>
</annotation>
