<annotation>
	<folder>Deadlock</folder>
	<filename>098.png</filename>
	<path>D:\temp\CSDQA\diagram\Deadlock\098.png</path>
	<source>
		<database>Unknown</database>
	</source>
	<size>
		<width>451</width>
		<height>400</height>
		<depth>1</depth>
	</size>
	<segmented>0</segmented>
	<object>
		<name>deadlock</name>
		<pose>Unspecified</pose>
		<truncated>0</truncated>
		<difficult>0</difficult>
		<bndbox>
			<xmin>16</xmin>
			<ymin>50</ymin>
			<xmax>440</xmax>
			<ymax>352</ymax>
		</bndbox>
	</object>
	<object>
		<name>answer</name>
		<pose>Unspecified</pose>
		<truncated>0</truncated>
		<difficult>0</difficult>
		<bndbox>
			<xmin>17</xmin>
			<ymin>50</ymin>
			<xmax>441</xmax>
			<ymax>352</ymax>
		</bndbox>
	</object>
</annotation>
