<annotation>
	<folder>Logic-circuit</folder>
	<filename>7.png</filename>
	<path>C:\Users\lenovo\Desktop\diagram\Logic-circuit\7.png</path>
	<source>
		<database>Unknown</database>
	</source>
	<size>
		<width>413</width>
		<height>176</height>
		<depth>3</depth>
	</size>
	<segmented>0</segmented>
	<object>
		<name>gate</name>
		<pose>Unspecified</pose>
		<truncated>0</truncated>
		<difficult>0</difficult>
		<bndbox>
			<xmin>76</xmin>
			<ymin>34</ymin>
			<xmax>212</xmax>
			<ymax>136</ymax>
		</bndbox>
	</object>
	<object>
		<name>circuit</name>
		<pose>Unspecified</pose>
		<truncated>0</truncated>
		<difficult>0</difficult>
		<bndbox>
			<xmin>10</xmin>
			<ymin>29</ymin>
			<xmax>296</xmax>
			<ymax>142</ymax>
		</bndbox>
	</object>
	<object>
		<name>input port</name>
		<pose>Unspecified</pose>
		<truncated>0</truncated>
		<difficult>0</difficult>
		<bndbox>
			<xmin>3</xmin>
			<ymin>45</ymin>
			<xmax>41</xmax>
			<ymax>77</ymax>
		</bndbox>
	</object>
	<object>
		<name>input port</name>
		<pose>Unspecified</pose>
		<truncated>0</truncated>
		<difficult>0</difficult>
		<bndbox>
			<xmin>3</xmin>
			<ymin>92</ymin>
			<xmax>43</xmax>
			<ymax>119</ymax>
		</bndbox>
	</object>
	<object>
		<name>output port</name>
		<pose>Unspecified</pose>
		<truncated>0</truncated>
		<difficult>0</difficult>
		<bndbox>
			<xmin>239</xmin>
			<ymin>70</ymin>
			<xmax>285</xmax>
			<ymax>100</ymax>
		</bndbox>
	</object>
</annotation>
