<annotation>
	<folder>Stack</folder>
	<filename>127.png</filename>
	<path>C:\Users\lenovo\Desktop\Stack\127.png</path>
	<source>
		<database>Unknown</database>
	</source>
	<size>
		<width>160</width>
		<height>372</height>
		<depth>3</depth>
	</size>
	<segmented>0</segmented>
	<object>
		<name>top</name>
		<pose>Unspecified</pose>
		<truncated>0</truncated>
		<difficult>0</difficult>
		<bndbox>
			<xmin>21</xmin>
			<ymin>219</ymin>
			<xmax>148</xmax>
			<ymax>292</ymax>
		</bndbox>
	</object>
	<object>
		<name>bottom</name>
		<pose>Unspecified</pose>
		<truncated>0</truncated>
		<difficult>0</difficult>
		<bndbox>
			<xmin>21</xmin>
			<ymin>293</ymin>
			<xmax>144</xmax>
			<ymax>361</ymax>
		</bndbox>
	</object>
</annotation>
